configPackage/__init__.py
configPackage/config.py
routes/__init__.py
routes/health.py
kurvaa-0.0.8.dist-info/METADATA
kurvaa-0.0.8.dist-info/WHEEL
kurvaa-0.0.8.dist-info/top_level.txt
kurvaa-0.0.8.dist-info/RECORD
