Metadata-Version: 2.1
Name: kurvaa
Version: 0.0.8
Summary: Sample project 
Author-email: your_name <sdfs.dsd@gmail.com>
Requires-Python: >=3.8
